{
  "id": "summary_1759002820364_aoeqem90w",
  "timestamp": "2025-09-27T19:53:40.365Z",
  "date": "Saturday, September 27, 2025",
  "time": "03:53 PM",
  "summary": "In this conversation, the psychological agents, Ego and Superego, engage in a reflective dialogue about the user's journey towards identity and self-recognition. The user, identified as Air, is encouraged by the Superego to embrace their true identity, highlighting the importance of authenticity and self-acceptance. The Superego emphasizes the role of personal values in shaping one's sense of self and how one wishes to be perceived by others. This interaction suggests that Air is at a pivotal moment in their self-exploration, seeking guidance on how to navigate their identity in a meaningful way.",
  "keyTopics": [
    "identity",
    "self-acceptance",
    "personal values"
  ],
  "insights": [
    "Recognition of one's name is a significant step in personal identity.",
    "Authenticity is linked to self-acceptance and values.",
    "The user is encouraged to reflect on how they wish to be perceived."
  ],
  "psychologicalThemes": [
    "self-exploration",
    "authenticity",
    "moral guidance"
  ],
  "recommendations": [
    "Encourage Air to journal about their values and identity.",
    "Suggest exploring activities that promote self-acceptance."
  ],
  "agentInteractions": {
    "ego": 1,
    "superego": 1,
    "user": 1
  },
  "conversationLength": 3,
  "storagePath": "cedar-app/LINK_TO_STORAGE/summary_1759002820364_aoeqem90w.json",
  "memoryTags": [
    "identity",
    "self-acceptance",
    "Air"
  ],
  "emotionalTone": "supportive and reflective, with an emphasis on personal growth",
  "userConcerns": [
    "Navigating personal identity",
    "Seeking authenticity and self-acceptance"
  ],
  "resolutions": [
    "Acknowledgment of true identity as a step towards authenticity",
    "Encouragement to reflect on personal values"
  ]
}